pi_screencontrol_webthing/__init__.py
pi_screencontrol_webthing/app.py
pi_screencontrol_webthing/screen.py
pi_screencontrol_webthing/screen_webthing.py
pi_screencontrol_webthing-0.1.6.dist-info/LICENSE
pi_screencontrol_webthing-0.1.6.dist-info/METADATA
pi_screencontrol_webthing-0.1.6.dist-info/WHEEL
pi_screencontrol_webthing-0.1.6.dist-info/entry_points.txt
pi_screencontrol_webthing-0.1.6.dist-info/top_level.txt
pi_screencontrol_webthing-0.1.6.dist-info/RECORD
